musicdl/__init__.py
musicdl/musicdl.py
musicdl/modules/__init__.py
musicdl/modules/audiobooks/__init__.py
musicdl/modules/audiobooks/lizhi.py
musicdl/modules/audiobooks/qingting.py
musicdl/modules/audiobooks/ximalaya.py
musicdl/modules/common/__init__.py
musicdl/modules/common/gdstudio.py
musicdl/modules/common/jbsou.py
musicdl/modules/common/mp3juice.py
musicdl/modules/common/myfreemp3.py
musicdl/modules/common/tunehub.py
musicdl/modules/js/__init__.py
musicdl/modules/js/youtube/__init__.py
musicdl/modules/js/youtube/botguard.js
musicdl/modules/js/youtube/jsinterp.py
musicdl/modules/js/youtube/runner.js
musicdl/modules/sources/__init__.py
musicdl/modules/sources/apple.py
musicdl/modules/sources/base.py
musicdl/modules/sources/bilibili.py
musicdl/modules/sources/buguyy.py
musicdl/modules/sources/fangpi.py
musicdl/modules/sources/fivesing.py
musicdl/modules/sources/fivesong.py
musicdl/modules/sources/flmp3.py
musicdl/modules/sources/gequbao.py
musicdl/modules/sources/gequhai.py
musicdl/modules/sources/htqyy.py
musicdl/modules/sources/jamendo.py
musicdl/modules/sources/jcpoo.py
musicdl/modules/sources/joox.py
musicdl/modules/sources/kkws.py
musicdl/modules/sources/kugou.py
musicdl/modules/sources/kuwo.py
musicdl/modules/sources/livepoo.py
musicdl/modules/sources/migu.py
musicdl/modules/sources/mitu.py
musicdl/modules/sources/netease.py
musicdl/modules/sources/qianqian.py
musicdl/modules/sources/qq.py
musicdl/modules/sources/soda.py
musicdl/modules/sources/tidal.py
musicdl/modules/sources/twot58.py
musicdl/modules/sources/yinyuedao.py
musicdl/modules/sources/youtube.py
musicdl/modules/sources/zhuolin.py
musicdl/modules/utils/__init__.py
musicdl/modules/utils/appleutils.py
musicdl/modules/utils/data.py
musicdl/modules/utils/importutils.py
musicdl/modules/utils/ip.py
musicdl/modules/utils/kuwoutils.py
musicdl/modules/utils/lanzouyparser.py
musicdl/modules/utils/logger.py
musicdl/modules/utils/lyric.py
musicdl/modules/utils/misc.py
musicdl/modules/utils/modulebuilder.py
musicdl-2.8.12.dist-info/LICENSE
musicdl-2.8.12.dist-info/METADATA
musicdl-2.8.12.dist-info/WHEEL
musicdl-2.8.12.dist-info/entry_points.txt
musicdl-2.8.12.dist-info/top_level.txt
musicdl-2.8.12.dist-info/zip-safe
musicdl-2.8.12.dist-info/RECORD
