Metadata-Version: 2.1
Name: musicdl
Version: 2.8.12
Summary: Musicdl: A lightweight music downloader written in pure python
Home-page: https://github.com/CharlesPikachu/musicdl
Author: Zhenchao Jin
Author-email: charlesblwx@gmail.com
License: Apache License 2.0
Classifier: License :: OSI Approved :: Apache Software License
Classifier: Programming Language :: Python :: 3
Classifier: Intended Audience :: Developers
Classifier: Operating System :: OS Independent
License-File: LICENSE
Requires-Dist: click
Requires-Dist: json-repair
Requires-Dist: prettytable
Requires-Dist: pycryptodome
Requires-Dist: orjson
Requires-Dist: requests
Requires-Dist: cryptography
Requires-Dist: fake-useragent
Requires-Dist: pathvalidate
Requires-Dist: rich
Requires-Dist: emoji
Requires-Dist: bleach
Requires-Dist: beautifulsoup4
Requires-Dist: aigpy
Requires-Dist: av
Requires-Dist: tabulate
Requires-Dist: mutagen
Requires-Dist: ytmusicapi
Requires-Dist: m3u8
Requires-Dist: pywidevine
Requires-Dist: tinytag
Requires-Dist: curl-cffi
Requires-Dist: platformdirs
Requires-Dist: lxml
Requires-Dist: prompt-toolkit
Requires-Dist: nodejs-wheel
